boto3_type_annotations/__init__.py
boto3_type_annotations/acm/__init__.py
boto3_type_annotations/acm/client.py
boto3_type_annotations/acm/paginator.py
boto3_type_annotations/acm/waiter.py
boto3_type_annotations/acm_pca/__init__.py
boto3_type_annotations/acm_pca/client.py
boto3_type_annotations/acm_pca/paginator.py
boto3_type_annotations/acm_pca/waiter.py
boto3_type_annotations/alexaforbusiness/__init__.py
boto3_type_annotations/alexaforbusiness/client.py
boto3_type_annotations/alexaforbusiness/paginator.py
boto3_type_annotations/amplify/__init__.py
boto3_type_annotations/amplify/client.py
boto3_type_annotations/amplify/paginator.py
boto3_type_annotations/apigateway/__init__.py
boto3_type_annotations/apigateway/client.py
boto3_type_annotations/apigateway/paginator.py
boto3_type_annotations/apigatewaymanagementapi/__init__.py
boto3_type_annotations/apigatewaymanagementapi/client.py
boto3_type_annotations/apigatewayv2/__init__.py
boto3_type_annotations/apigatewayv2/client.py
boto3_type_annotations/apigatewayv2/paginator.py
boto3_type_annotations/application_autoscaling/__init__.py
boto3_type_annotations/application_autoscaling/client.py
boto3_type_annotations/application_autoscaling/paginator.py
boto3_type_annotations/appmesh/__init__.py
boto3_type_annotations/appmesh/client.py
boto3_type_annotations/appmesh/paginator.py
boto3_type_annotations/appstream/__init__.py
boto3_type_annotations/appstream/client.py
boto3_type_annotations/appstream/paginator.py
boto3_type_annotations/appstream/waiter.py
boto3_type_annotations/appsync/__init__.py
boto3_type_annotations/appsync/client.py
boto3_type_annotations/appsync/paginator.py
boto3_type_annotations/athena/__init__.py
boto3_type_annotations/athena/client.py
boto3_type_annotations/athena/paginator.py
boto3_type_annotations/autoscaling/__init__.py
boto3_type_annotations/autoscaling/client.py
boto3_type_annotations/autoscaling/paginator.py
boto3_type_annotations-0.3.0.dist-info/DESCRIPTION.rst
boto3_type_annotations-0.3.0.dist-info/METADATA
boto3_type_annotations-0.3.0.dist-info/RECORD
boto3_type_annotations-0.3.0.dist-info/WHEEL
boto3_type_annotations-0.3.0.dist-info/metadata.json
boto3_type_annotations-0.3.0.dist-info/top_level.txt
