Metadata-Version: 2.0
Name: boto3-type-annotations
Version: 0.3.0
Summary: Type annotations for boto3. Adds code completion in IDEs such as PyCharm.
Home-page: https://github.com/alliefitter/boto3_type_annotations
Author: Allie Fitter
Author-email: fitterj@gmail.com
License: MIT License
Platform: UNKNOWN
Classifier: Programming Language :: Python :: 3
Classifier: License :: OSI Approved :: MIT License
Classifier: Operating System :: OS Independent
